{
  "日期": "20251029",
  "采集时间": "2025-10-29 19:11:00",
  "涨停板总数": 60,
  "竞价阶段封板数": 5,
  "最大封单额": 664560676.0,
  "最大封单股票": "000592-平潭发展",
  "平均封单额": 113424845.03333333,
  "封单额中位数": 79832404.0,
  "时间段分布": {
    "下午盘(13:00-15:00)": 20,
    "开盘初期(09:30-10:00)": 16,
    "其他时间": 10,
    "上午盘(10:00-11:30)": 9,
    "竞价阶段(09:15-09:25)": 5
  },
  "前10大封单": [
    {
      "代码": "000592",
      "名称": "平潭发展",
      "封板资金": 664560676,
      "首次封板时间": "092500"
    },
    {
      "代码": "000981",
      "名称": "山子高科",
      "封板资金": 512111273,
      "首次封板时间": "093036"
    },
    {
      "代码": "601012",
      "名称": "隆基绿能",
      "封板资金": 441328498,
      "首次封板时间": "131403"
    },
    {
      "代码": "605178",
      "名称": "时空科技",
      "封板资金": 351428507,
      "首次封板时间": "092503"
    },
    {
      "代码": "000657",
      "名称": "中钨高新",
      "封板资金": 343614328,
      "首次封板时间": "093124"
    },
    {
      "代码": "002790",
      "名称": "瑞尔特",
      "封板资金": 273049951,
      "首次封板时间": "092500"
    },
    {
      "代码": "600516",
      "名称": "方大炭素",
      "封板资金": 202804856,
      "首次封板时间": "101824"
    },
    {
      "代码": "002150",
      "名称": "通润装备",
      "封板资金": 201396316,
      "首次封板时间": "104524"
    },
    {
      "代码": "000555",
      "名称": "神州信息",
      "封板资金": 197449133,
      "首次封板时间": "094212"
    },
    {
      "代码": "002163",
      "名称": "海南发展",
      "封板资金": 154653015,
      "首次封板时间": "093651"
    }
  ]
}